prot2vec/__init__.py
prot2vec/constants.py
prot2vec/analysis/__init__.py
prot2vec/analysis/index_accuracy.py
prot2vec/analysis/sentencepiece_and_protein_accuracy.py
prot2vec/callbacks/__init__.py
prot2vec/callbacks/experiment_logger.py
prot2vec/callbacks/hint_termostat.py
prot2vec/datasets/__init__.py
prot2vec/datasets/amino_acid.py
prot2vec/datasets/amino_acid_1aa_confusion_test.py
prot2vec/datasets/amino_acid_2aa_confusion_test.py
prot2vec/datasets/amino_acid_entangl.py
prot2vec/datasets/amino_acid_hints.py
prot2vec/datasets/amino_acid_overlaping_triplets.py
prot2vec/datasets/amino_acids_different_protein.py
prot2vec/datasets/cipher_amino_acid.py
prot2vec/datasets/pfam_clan_prediciton.py
prot2vec/datasets/sentence_piece.py
prot2vec/datasets/sentence_piece_analysis.py
prot2vec/datasets/sentence_piece_changing_hints.py
prot2vec/datasets/sentence_piece_termostat.py
prot2vec/datasets/svec_compatible.py
prot2vec/layers/__init__.py
prot2vec/layers/ioembedding.py
prot2vec/layers/resnet.py
prot2vec/layers/skip_block_conv1d.py
prot2vec/layers/transformer_block.py
prot2vec/metrics/__init__.py
prot2vec/metrics/accuracy_masked.py
prot2vec/metrics/accuracy_without_pad.py
prot2vec/metrics/crossentropy_masked.py
prot2vec/metrics/index_accuracy_histogram.py
prot2vec/metrics/mean_top_k.py
prot2vec/metrics/sample_accuracy_histogram.py
prot2vec/metrics/top_k_accuracy_without_pad.py
prot2vec/models/__init__.py
prot2vec/models/bert.py
prot2vec/models/cnn_bert.py
prot2vec/models/conv1D_amino_acid.py
prot2vec/models/conv_autoencoder.py
prot2vec/models/decipher.py
prot2vec/models/pfam_clan_prediction.py
prot2vec/models/svec_bert_fill_and_reconstruct.py
prot2vec-0.0.78.dist-info/LICENSE
prot2vec-0.0.78.dist-info/METADATA
prot2vec-0.0.78.dist-info/WHEEL
prot2vec-0.0.78.dist-info/top_level.txt
prot2vec-0.0.78.dist-info/RECORD
