Metadata-Version: 2.1
Name: prot2vec
Version: 0.0.78
Summary: Vectorization and Annotation of Protein Sequences
Home-page: UNKNOWN
Author: Tomas Honzik
Author-email: <tomas.honziik@seznam.cz>
License: UNKNOWN
Keywords: python,protein
Platform: UNKNOWN
Classifier: Development Status :: 1 - Planning
Classifier: Intended Audience :: Developers
Classifier: Programming Language :: Python :: 3
Classifier: Operating System :: Unix
Classifier: Operating System :: MacOS :: MacOS X
Classifier: Operating System :: Microsoft :: Windows
